ldap3/__init__.py
ldap3/version.py
ldap3/abstract/__init__.py
ldap3/abstract/attrDef.py
ldap3/abstract/attribute.py
ldap3/abstract/cursor.py
ldap3/abstract/entry.py
ldap3/abstract/objectDef.py
ldap3/core/__init__.py
ldap3/core/connection.py
ldap3/core/exceptions.py
ldap3/core/pooling.py
ldap3/core/rdns.py
ldap3/core/results.py
ldap3/core/server.py
ldap3/core/timezone.py
ldap3/core/tls.py
ldap3/core/usage.py
ldap3/extend/__init__.py
ldap3/extend/operation.py
ldap3/extend/microsoft/__init__.py
ldap3/extend/microsoft/addMembersToGroups.py
ldap3/extend/microsoft/dirSync.py
ldap3/extend/microsoft/fastBind.py
ldap3/extend/microsoft/modifyPassword.py
ldap3/extend/microsoft/persistentSearch.py
ldap3/extend/microsoft/removeMembersFromGroups.py
ldap3/extend/microsoft/unlockAccount.py
ldap3/extend/novell/__init__.py
ldap3/extend/novell/addMembersToGroups.py
ldap3/extend/novell/checkGroupsMemberships.py
ldap3/extend/novell/endTransaction.py
ldap3/extend/novell/getBindDn.py
ldap3/extend/novell/listReplicas.py
ldap3/extend/novell/nmasGetUniversalPassword.py
ldap3/extend/novell/nmasSetUniversalPassword.py
ldap3/extend/novell/partition_entry_count.py
ldap3/extend/novell/removeMembersFromGroups.py
ldap3/extend/novell/replicaInfo.py
ldap3/extend/novell/startTransaction.py
ldap3/extend/standard/PagedSearch.py
ldap3/extend/standard/PersistentSearch.py
ldap3/extend/standard/__init__.py
ldap3/extend/standard/modifyPassword.py
ldap3/extend/standard/whoAmI.py
ldap3/operation/__init__.py
ldap3/operation/abandon.py
ldap3/operation/add.py
ldap3/operation/bind.py
ldap3/operation/compare.py
ldap3/operation/delete.py
ldap3/operation/extended.py
ldap3/operation/modify.py
ldap3/operation/modifyDn.py
ldap3/operation/search.py
ldap3/operation/unbind.py
ldap3/protocol/__init__.py
ldap3/protocol/controls.py
ldap3/protocol/convert.py
ldap3/protocol/microsoft.py
ldap3/protocol/novell.py
ldap3/protocol/oid.py
ldap3/protocol/persistentSearch.py
ldap3/protocol/rfc2696.py
ldap3/protocol/rfc2849.py
ldap3_bleeding_edge-2.10.1.1338.dist-info/COPYING.LESSER.txt
ldap3_bleeding_edge-2.10.1.1338.dist-info/COPYING.txt
ldap3_bleeding_edge-2.10.1.1338.dist-info/LICENSE.txt
ldap3_bleeding_edge-2.10.1.1338.dist-info/METADATA
ldap3_bleeding_edge-2.10.1.1338.dist-info/WHEEL
ldap3_bleeding_edge-2.10.1.1338.dist-info/top_level.txt
ldap3_bleeding_edge-2.10.1.1338.dist-info/RECORD
