Metadata-Version: 2.2
Name: ldap3-bleeding_edge
Version: 2.10.1.1338
Summary: A strictly RFC 4510 conforming LDAP V3 pure Python client library (bleeding edge)
Home-page: https://github.com/ThePirateWhoSmellsOfSunflowers/ldap3/tree/bleeding_edge
Author: Giovanni Cannata / ThePirateWhoSmellsOfSunflowers
Author-email: cannatag@gmail.com
License: LGPL v3
Keywords: python3 python2 ldap
Classifier: Development Status :: 5 - Production/Stable
Classifier: Intended Audience :: Developers
Classifier: Intended Audience :: System Administrators
Classifier: Operating System :: MacOS :: MacOS X
Classifier: Operating System :: Microsoft :: Windows
Classifier: Operating System :: POSIX :: Linux
Classifier: License :: OSI Approved :: GNU Lesser General Public License v3 (LGPLv3)
Classifier: Programming Language :: Python
Classifier: Programming Language :: Python :: 2
Classifier: Programming Language :: Python :: 3
Classifier: Topic :: Software Development :: Libraries :: Python Modules
Classifier: Topic :: System :: Systems Administration :: Authentication/Directory :: LDAP
License-File: LICENSE.txt
License-File: COPYING.LESSER.txt
License-File: COPYING.txt
Requires-Dist: pyasn1>=0.4.6
Requires-Dist: pycryptodomex
Requires-Dist: cryptography
Provides-Extra: kerberos
Requires-Dist: winkerberos; platform_system == "Windows" and extra == "kerberos"
Requires-Dist: gssapi; platform_system != "Windows" and extra == "kerberos"
Dynamic: author
Dynamic: author-email
Dynamic: classifier
Dynamic: description
Dynamic: home-page
Dynamic: keywords
Dynamic: license
Dynamic: provides-extra
Dynamic: requires-dist
Dynamic: summary
